git_storage/__init__.py
git_storage/apps.py
git_storage/base.py
git_storage/storage.py
django_git_storages-1.0.0.dist-info/METADATA
django_git_storages-1.0.0.dist-info/WHEEL
django_git_storages-1.0.0.dist-info/top_level.txt
django_git_storages-1.0.0.dist-info/RECORD
