Metadata-Version: 2.1
Name: django-git-storages
Version: 1.0.0
Summary: Django Github Storage Package 
Home-page: https://github.com/debugtitan/django-git-storage
Author: Uche David
Author-email: debugtitan.hub@outlook.com
License: MIT
Keywords: django git storage,django github storage
Classifier: Framework :: Django
Classifier: Programming Language :: Python :: 3
